pymldb/__init__.py
pymldb/data.py
pymldb/index.py
pymldb/magic.py
pymldb/progress_monitor.py
pymldb/query.py
pymldb/steps_logger.py
pymldb/test.py
pymldb/util.py
pymldb/version.py
pymldb-0.8.1.dist-info/DESCRIPTION.rst
pymldb-0.8.1.dist-info/METADATA
pymldb-0.8.1.dist-info/RECORD
pymldb-0.8.1.dist-info/WHEEL
pymldb-0.8.1.dist-info/metadata.json
pymldb-0.8.1.dist-info/top_level.txt
