Metadata-Version: 2.0
Name: pymldb
Version: 0.8.1
Summary: Python interface to MLDB
Home-page: https://github.com/datacratic/pymldb
Author: Datacratic
Author-email: mldb@datacratic.com
License: BSD
Keywords: machine learning
Platform: UNKNOWN
Classifier: Development Status :: 3 - Alpha
Classifier: License :: OSI Approved :: BSD License
Classifier: Programming Language :: Python :: 2
Classifier: Intended Audience :: Developers
Classifier: Topic :: Database :: Database Engines/Servers
Classifier: Topic :: Scientific/Engineering :: Mathematics
Classifier: Topic :: Scientific/Engineering :: Artificial Intelligence
Requires-Dist: numpy
Requires-Dist: pandas
Requires-Dist: pygments
Requires-Dist: requests[security] (>=2.6)
